sigma/backends/insight_idr/__init__.py
sigma/backends/insight_idr/insight_idr.py
sigma/pipelines/insight_idr/__init__.py
sigma/pipelines/insight_idr/insight_idr.py
pysigma_backend_insightidr-0.2.4.dist-info/LICENSE
pysigma_backend_insightidr-0.2.4.dist-info/METADATA
pysigma_backend_insightidr-0.2.4.dist-info/WHEEL
pysigma_backend_insightidr-0.2.4.dist-info/RECORD
