Metadata-Version: 2.1
Name: pysigma-backend-insightidr
Version: 0.2.4
Summary: pySigma Rapid7 InsightIDR backend
Home-page: https://github.com/SigmaHQ/pySigma-backend-insightidr
License: LGPL-2.1-only
Author: Micah Babinski
Author-email: m.babinski.88@gmail.com
Requires-Python: >=3.8,<4.0
Classifier: License :: OSI Approved
Classifier: Programming Language :: Python :: 3
Classifier: Programming Language :: Python :: 3.8
Classifier: Programming Language :: Python :: 3.9
Classifier: Programming Language :: Python :: 3.10
Classifier: Programming Language :: Python :: 3.11
Classifier: Programming Language :: Python :: 3.12
Requires-Dist: pysigma (>=0.10.1,<0.12.0)
Project-URL: Repository, https://github.com/SigmaHQ/pySigma-backend-insightidr
